jiraX/__init__.py
jiraX/backlog.py
jiraX/base.py
jiraX/board.py
jiraX/comment.py
jiraX/factories.py
jiraX/issue.py
jiraX/project.py
jiraX/role.py
jiraX/sprint.py
jiraX/sprintbacklog.py
jiraX/user.py
jiraA-0.0.19.dist-info/METADATA
jiraA-0.0.19.dist-info/WHEEL
jiraA-0.0.19.dist-info/top_level.txt
jiraA-0.0.19.dist-info/RECORD
