Metadata-Version: 2.1
Name: jiraA
Version: 0.0.19
Summary: Lib created based on documentaion https://docs.atlassian.com/DAC/rest/jira/6.1.html
Home-page: https://gitlab.com/integration_seon/libs/application/jira
Author: Paulo Sérgio dos Santos Júnior
Author-email: paulossjunior@gmail.com
License: UNKNOWN
Platform: UNKNOWN
Classifier: Programming Language :: Python :: 3
Classifier: License :: OSI Approved :: MIT License
Classifier: Operating System :: OS Independent
Requires-Dist: factory-boy ==3.0.1
Requires-Dist: jira ==3.8.0
